polyaxon_dockerizer/__init__.py
polyaxon_dockerizer/builder.py
polyaxon_dockerizer/constants.py
polyaxon_dockerizer/dockerfile.py
polyaxon_dockerizer/exceptions.py
polyaxon_dockerizer/generator.py
tests/__init__.py
tests/test_builder.py
tests/test_dockerfile_generator.py
polyaxon_dockerizer-0.1.0.dist-info/LICENSE
polyaxon_dockerizer-0.1.0.dist-info/METADATA
polyaxon_dockerizer-0.1.0.dist-info/WHEEL
polyaxon_dockerizer-0.1.0.dist-info/top_level.txt
polyaxon_dockerizer-0.1.0.dist-info/RECORD
