Metadata-Version: 2.1
Name: polyaxon-dockerizer
Version: 0.1.0
Summary: Python dockerizer to generate and build docker images.
Home-page: https://github.com/polyaxon/polyaxon-dockerizer
Author: Mourad Mourafiq
Author-email: mourad@polyaxon.com
Maintainer: Mourad Mourafiq
Maintainer-email: mourad@polyaxon.com
License: MIT
Keywords: polyaxon,docker,deep-learning,machine-learning,data-science,neural-networks,artificial-intelligence,ai,reinforcement-learning,kubernetes
Platform: any
Classifier: Programming Language :: Python
Classifier: Operating System :: OS Independent
Classifier: Intended Audience :: Developers
Classifier: Intended Audience :: Science/Research
Classifier: Topic :: Scientific/Engineering :: Artificial Intelligence
Requires-Dist: docker (==4.1.0)
Requires-Dist: Unipath (==1.1)
